{
  "type": "FeatureCollection",
  "generator": "smartcity",
  "copyright": "Smartcity",
  "timestamp": "2021-05-27T09:28:58Z",
  "features": [
    {
      "type": "Feature",
      "properties": {
        "Building name": "Bậc 3 cầu thang bên trái",
        "height": 1,
        "width": 15,
        "color": "#838b94",
        "idb": "1"
      },
      "geometry": {
        "type": "Polygon",
        "coordinates": [
          [
            [105.834736024, 21.036402158, 0.8],
            [105.83476642770303, 21.036534037720802, 0.8],
            [105.83481044307938, 21.036524976271224, 0.8],
            [105.83477930600993, 21.036393245697152, 0.8]
          ]
        ]
      },
      "id": "pp1"
    }
  ]
}
