{
    "type": "FeatureCollection",
    "generator": "smartcity",
    "copyright": "Smartcity",
    "timestamp": "2021-05-27T09:28:58Z",
    "features": [
      {
        "type": "Feature",
        "properties": {
          "Building name": "Cửa 1 chính diện lầu 1 gian giữa",
          "height": 3.54,
          "width": 0.8192,
          "color": "#5D1C15",
          "idb": "1"
        },
        "geometry": {
          "type": "Polygon",
          "coordinates": [
            [[107.57917013691046,16.46780890937903,6.24],[107.57916997104499,16.46780912729714,6.24],[107.5791761764292,16.46781347052523,6.24],[107.57917634227891,16.46781325259039,6.24]]
          ]
        },
        "id": "pp1"
      }
    ]
  }
  