{
  "type": "FeatureCollection",
  "generator": "smartcity",
  "copyright": "Smartcity",
  "timestamp": "2021-05-27T09:28:58Z",
  "features": [
    {
      "type": "Feature",
      "properties": {
        "Building name": "Thanh lề ngang gia cố cửa 14 hông phải tầng 2 tòa phải",
        "height": 0.04,
        "width": 0.567,
        "color": "#701a1d",
        "idb": "1"
      },
      "geometry": {
        "type": "Polygon",
        "coordinates": [
          [
            [107.57928331322445, 16.467783855210616, 10.38],
            [107.57928342379499, 16.4677837099254, 10.38],
            [107.57926826564723, 16.467773879904186, 10.38],
            [107.57926815507405, 16.467774025187552, 10.38]
          ]
        ]
      },
      "id": "pp1"
    }
  ]
}
