{
  "type": "FeatureCollection",
  "generator": "smartcity",
  "copyright": "Smartcity",
  "timestamp": "2021-05-27T09:28:58Z",
  "features": [
    {
      "type": "Feature",
      "properties": {
        "Building name": "Cửa 6 phía sau tầng 2 tòa phải",
        "height": 1.4,
        "width": 0.567,
        "color": "#bb853a",
        "idb": "1"
      },
      "geometry": {
        "type": "Polygon",
        "coordinates": [
          [
            [107.57924090660889, 16.467793810411575, 10.38],
            [107.57924074075127, 16.467794028338037, 10.38],
            [107.57924831569697, 16.467799330140394, 10.38],
            [107.57924848155461, 16.46779911221393, 10.38]
          ]
        ]
      },
      "id": "pp1"
    }
  ]
}
