{
  "type": "FeatureCollection",
  "generator": "smartcity",
  "copyright": "Smartcity",
  "timestamp": "2021-05-27T09:28:58Z",
  "features": [
    {
      "type": "Feature",
      "properties": {
        "Building name": "Cột 21 tòa bên phải",
        "height": 5.0,
        "width": 0.5,
        "color": "#3B1311",
        "idb": "1"
      },
      "geometry": {
        "type": "Polygon",
        "coordinates": [
          [
            [
              107.57933727980871,
              16.46785826524028,
              4.94
            ],
            [
              107.57933727518761,
              16.467858412285814,
              4.94
            ],
            [
              107.57933726134257,
              16.467858558751022,
              4.94
            ],
            [
              107.57933723832824,
              16.46785870405788,
              4.94
            ],
            [
              107.57933720623541,
              16.46785884763292,
              4.94
            ],
            [
              107.57933716519076,
              16.46785898890953,
              4.94
            ],
            [
              107.57933711535627,
              16.467859127330144,
              4.94
            ],
            [
              107.57933705692862,
              16.467859262348483,
              4.94
            ],
            [
              107.57933699013839,
              16.467859393431695,
              4.94
            ],
            [
              107.57933691524917,
              16.467859520062447,
              4.94
            ],
            [
              107.57933683255652,
              16.46785964174099,
              4.94
            ],
            [
              107.57933674238679,
              16.467859757987114,
              4.94
            ],
            [
              107.57933664509582,
              16.46785986834205,
              4.94
            ],
            [
              107.57933654106759,
              16.467859972370274,
              4.94
            ],
            [
              107.57933643071266,
              16.467860069661235,
              4.94
            ],
            [
              107.57933631446653,
              16.467860159830973,
              4.94
            ],
            [
              107.57933619278799,
              16.467860242523624,
              4.94
            ],
            [
              107.57933606615724,
              16.467860317412843,
              4.94
            ],
            [
              107.57933593507403,
              16.467860384203075,
              4.94
            ],
            [
              107.57933580005569,
              16.467860442630727,
              4.94
            ],
            [
              107.57933566163507,
              16.467860492465217,
              4.94
            ],
            [
              107.57933552035847,
              16.467860533509864,
              4.94
            ],
            [
              107.57933537678342,
              16.467860565602688,
              4.94
            ],
            [
              107.57933523147656,
              16.467860588617032,
              4.94
            ],
            [
              107.57933508501135,
              16.46786060246207,
              4.94
            ],
            [
              107.57933493796583,
              16.467860607083164,
              4.94
            ],
            [
              107.5793347909203,
              16.46786060246207,
              4.94
            ],
            [
              107.57933464445509,
              16.467860588617032,
              4.94
            ],
            [
              107.57933449914823,
              16.467860565602688,
              4.94
            ],
            [
              107.57933435557318,
              16.467860533509864,
              4.94
            ],
            [
              107.57933421429658,
              16.467860492465217,
              4.94
            ],
            [
              107.57933407587596,
              16.467860442630727,
              4.94
            ],
            [
              107.57933394085762,
              16.467860384203075,
              4.94
            ],
            [
              107.57933380977441,
              16.467860317412843,
              4.94
            ],
            [
              107.57933368314366,
              16.467860242523624,
              4.94
            ],
            [
              107.57933356146512,
              16.467860159830973,
              4.94
            ],
            [
              107.57933344521899,
              16.467860069661235,
              4.94
            ],
            [
              107.57933333486406,
              16.467859972370274,
              4.94
            ],
            [
              107.57933323083583,
              16.46785986834205,
              4.94
            ],
            [
              107.57933313354486,
              16.467859757987114,
              4.94
            ],
            [
              107.57933304337513,
              16.46785964174099,
              4.94
            ],
            [
              107.57933296068248,
              16.467859520062447,
              4.94
            ],
            [
              107.57933288579326,
              16.467859393431695,
              4.94
            ],
            [
              107.57933281900303,
              16.467859262348483,
              4.94
            ],
            [
              107.57933276057538,
              16.467859127330144,
              4.94
            ],
            [
              107.57933271074089,
              16.46785898890953,
              4.94
            ],
            [
              107.57933266969624,
              16.46785884763292,
              4.94
            ],
            [
              107.57933263760341,
              16.46785870405788,
              4.94
            ],
            [
              107.57933261458908,
              16.467858558751022,
              4.94
            ],
            [
              107.57933260074404,
              16.467858412285814,
              4.94
            ],
            [
              107.57933259612294,
              16.46785826524028,
              4.94
            ],
            [
              107.57933260074404,
              16.467858118194748,
              4.94
            ],
            [
              107.57933261458908,
              16.46785797172954,
              4.94
            ],
            [
              107.57933263760341,
              16.467857826422684,
              4.94
            ],
            [
              107.57933266969624,
              16.46785768284764,
              4.94
            ],
            [
              107.57933271074089,
              16.467857541571032,
              4.94
            ],
            [
              107.57933276057538,
              16.46785740315042,
              4.94
            ],
            [
              107.57933281900303,
              16.46785726813208,
              4.94
            ],
            [
              107.57933288579326,
              16.467857137048867,
              4.94
            ],
            [
              107.57933296068248,
              16.467857010418115,
              4.94
            ],
            [
              107.57933304337513,
              16.467856888739572,
              4.94
            ],
            [
              107.57933313354486,
              16.467856772493448,
              4.94
            ],
            [
              107.57933323083583,
              16.467856662138512,
              4.94
            ],
            [
              107.57933333486406,
              16.467856558110288,
              4.94
            ],
            [
              107.57933344521899,
              16.467856460819327,
              4.94
            ],
            [
              107.57933356146512,
              16.46785637064959,
              4.94
            ],
            [
              107.57933368314366,
              16.467856287956938,
              4.94
            ],
            [
              107.57933380977441,
              16.46785621306772,
              4.94
            ],
            [
              107.57933394085762,
              16.467856146277487,
              4.94
            ],
            [
              107.57933407587596,
              16.467856087849835,
              4.94
            ],
            [
              107.57933421429658,
              16.467856038015345,
              4.94
            ],
            [
              107.57933435557318,
              16.467855996970698,
              4.94
            ],
            [
              107.57933449914823,
              16.467855964877874,
              4.94
            ],
            [
              107.57933464445509,
              16.46785594186353,
              4.94
            ],
            [
              107.5793347909203,
              16.46785592801849,
              4.94
            ],
            [
              107.57933493796583,
              16.467855923397398,
              4.94
            ],
            [
              107.57933508501135,
              16.46785592801849,
              4.94
            ],
            [
              107.57933523147656,
              16.46785594186353,
              4.94
            ],
            [
              107.57933537678342,
              16.467855964877874,
              4.94
            ],
            [
              107.57933552035847,
              16.467855996970698,
              4.94
            ],
            [
              107.57933566163507,
              16.467856038015345,
              4.94
            ],
            [
              107.57933580005569,
              16.467856087849835,
              4.94
            ],
            [
              107.57933593507403,
              16.467856146277487,
              4.94
            ],
            [
              107.57933606615724,
              16.46785621306772,
              4.94
            ],
            [
              107.57933619278799,
              16.467856287956938,
              4.94
            ],
            [
              107.57933631446653,
              16.46785637064959,
              4.94
            ],
            [
              107.57933643071266,
              16.467856460819327,
              4.94
            ],
            [
              107.57933654106759,
              16.467856558110288,
              4.94
            ],
            [
              107.57933664509582,
              16.467856662138512,
              4.94
            ],
            [
              107.57933674238679,
              16.467856772493448,
              4.94
            ],
            [
              107.57933683255652,
              16.467856888739572,
              4.94
            ],
            [
              107.57933691524917,
              16.467857010418115,
              4.94
            ],
            [
              107.57933699013839,
              16.467857137048867,
              4.94
            ],
            [
              107.57933705692862,
              16.46785726813208,
              4.94
            ],
            [
              107.57933711535627,
              16.46785740315042,
              4.94
            ],
            [
              107.57933716519076,
              16.467857541571032,
              4.94
            ],
            [
              107.57933720623541,
              16.46785768284764,
              4.94
            ],
            [
              107.57933723832824,
              16.467857826422684,
              4.94
            ],
            [
              107.57933726134257,
              16.46785797172954,
              4.94
            ],
            [
              107.57933727518761,
              16.467858118194748,
              4.94
            ]
          ]
        ]
      },
      "id": "pp1"
    }
  ]
}