{
  "type": "FeatureCollection",
  "generator": "smartcity",
  "copyright": "Smartcity",
  "timestamp": "2021-05-27T09:28:58Z",
  "features": [
    {
      "type": "Feature",
      "properties": {
        "Building name": "Cửa 17 chính diện lầu 2 gian giữa",
        "height": 2,
        "width": 0.8275,
        "color": "#6b1f1f",
        "idb": "1"
      },
      "geometry": {
        "type": "Polygon",
        "coordinates": [
          [
            [107.57921736035996, 16.467740535263044, 9.78],
            [107.57921719450384, 16.467740753188007, 9.78],
            [107.57922346276932, 16.46774514042967, 9.78],
            [107.57922362862837, 16.467744922501762, 9.78]
          ]
        ]
      },
      "id": "pp1"
    }
  ]
}
