{
  "type": "FeatureCollection",
  "generator": "smartcity",
  "copyright": "Smartcity",
  "timestamp": "2021-05-27T09:28:58Z",
  "features": [
    {
      "type": "Feature",
      "properties": {
        "Building name": "Thanh lề dọc gia cố cửa 3 hông phải tầng 2 tòa giữa",
        "height": 1.4,
        "width": 0.02,
        "color": "#701a1d",
        "idb": "1"
      },
      "geometry": {
        "type": "Polygon",
        "coordinates": [
          [
            [107.5793397294742, 16.467752508176588, 10.38],
            [107.5793401082239, 16.46775277326323, 10.38],
            [107.57933983179686, 16.46775313647049, 10.38],
            [107.57933945305213, 16.467752871376856, 10.38]
          ]
        ]
      },
      "id": "pp1"
    }
  ]
}
