{
  "type": "FeatureCollection",
  "generator": "smartcity",
  "copyright": "Smartcity",
  "timestamp": "2021-05-27T09:28:58Z",
  "features": [
    {
      "type": "Feature",
      "properties": {
        "Building name": "Cửa 1 hông trái tầng 2 tòa phải",
        "height": 1.4,
        "width": 0.567,
        "color": "#bb853a",
        "idb": "1"
      },
      "geometry": {
        "type": "Polygon",
        "coordinates": [
          [
            [107.57933241739069, 16.467762420894708, 10.38],
            [107.57933264464157, 16.467762579945344, 10.38],
            [107.57932711605322, 16.467769844157274, 10.38],
            [107.57932688880743, 16.467769685099796, 10.38]
          ]
        ]
      },
      "id": "pp1"
    }
  ]
}
